jlproj/__init__.py
jlproj/cli.py
jlproj/faiss_wrapper.py
jlproj/projector.py
jlproj/utils.py
jlproj-0.1.8.dist-info/METADATA
jlproj-0.1.8.dist-info/WHEEL
jlproj-0.1.8.dist-info/entry_points.txt
jlproj-0.1.8.dist-info/top_level.txt
jlproj-0.1.8.dist-info/RECORD
