Metadata-Version: 2.4
Name: jlproj
Version: 0.1.8
Summary: Johnson–Lindenstrauss Projection Toolkit for dimensionality reduction
Home-page: https://github.com/Quchluk/jlproj
Author: Anton Smirnov
Author-email: Anton Smirnov <AntonSmirnovM@protonmail.com>
License-Expression: MIT
Requires-Python: >=3.8
Requires-Dist: numpy
Requires-Dist: faiss-cpu
Requires-Dist: scikit-learn
Requires-Dist: sentence-transformers
Dynamic: author
Dynamic: home-page
Dynamic: requires-python
